faser/__init__.py
faser/env.py
faser/io.py
faser/napari.yaml
faser/assets/Figure_ab.png
faser/assets/Figure_beam.png
faser/assets/Figure_geom.png
faser/assets/Figure_simu.png
faser/assets/batch.png
faser/assets/load.png
faser/assets/placeholder.png
faser/assets/refresh.png
faser/assets/save.png
faser/assets/single.png
faser/cli/__init__.py
faser/cli/main.py
faser/cli/qtmain.py
faser/generators/__init__.py
faser/generators/base.py
faser/generators/utils.py
faser/generators/scalar/__init__.py
faser/generators/scalar/gibson_lanny/PSFGenerator.jar
faser/generators/scalar/gibson_lanny/__init__.py
faser/generators/scalar/gibson_lanny/config.txt
faser/generators/scalar/gibson_lanny/gen.py
faser/generators/scalar/phasenet/__init__.py
faser/generators/scalar/phasenet/generator.py
faser/generators/scalar/phasenet/wavefront.py
faser/generators/vectorial/__init__.py
faser/generators/vectorial/utils.py
faser/generators/vectorial/stephane/__init__.py
faser/generators/vectorial/stephane/april_version.py
faser/generators/vectorial/stephane/tilted_compiled.py
faser/generators/vectorial/stephane/tilted_coverslip.py
faser/napari/__init__.py
faser/napari/gui.py
faser/napari/main.py
faser/napari/widgets/export.py
faser/napari/widgets/fields.py
faser/napari/widgets/helper_widget.py
faser/napari/widgets/main_widget.py
faser/napari/widgets/mpl_canvas.py
faser/napari/widgets/tob_bar.py
faser/napari.yaml
faser-0.3.6.dist-info/METADATA
faser-0.3.6.dist-info/WHEEL
faser-0.3.6.dist-info/entry_points.txt
faser-0.3.6.dist-info/licenses/LICENSE
faser-0.3.6.dist-info/RECORD
