Metadata-Version: 2.4
Name: faser
Version: 0.3.6
Summary: Faser is a tool for vectorial psf simulation
Project-URL: Bug Tracker, https://jhnnsrs.github.io/faser/issues
Project-URL: Documentation, https://jhnnsrs.github.io/faser
Project-URL: Source Code, https://github.com/jhnnsrs/faser
Author-email: Johannes Roos <jhnnsrs@gmail.com>, Stephane Bancelin <stephane.bancelin@cnrs.fr>
Maintainer-email: Johannes Roos <jhnnsrs@gmail.com>
License: 
License-File: LICENSE
Keywords: faser,napari,psf,simulation,vectorial
Classifier: Framework :: napari
Classifier: Programming Language :: Python
Classifier: Programming Language :: Python :: 3
Classifier: Programming Language :: Python :: 3 :: Only
Classifier: Programming Language :: Python :: 3.9
Classifier: Programming Language :: Python :: 3.10
Classifier: Programming Language :: Python :: 3.11
Classifier: Programming Language :: Python :: 3.12
Requires-Python: <3.13,>=3.9
Requires-Dist: matplotlib>=3.9.2
Requires-Dist: numpy<2
Requires-Dist: psygnal>=0.11.1
Requires-Dist: pydantic>2
Requires-Dist: python-slugify>=8.0.4
Requires-Dist: qtpy>=2.4.2
Requires-Dist: superqt>=0.6.7
Requires-Dist: tifffile>=2024.8.30
Provides-Extra: cli
Requires-Dist: rich-click>=1.8.3; extra == 'cli'
Provides-Extra: full
Requires-Dist: pyqt5>=5.15.11; extra == 'full'
Requires-Dist: rich-click>=1.8.3; extra == 'full'
Provides-Extra: numba
Requires-Dist: numba>=0.60.0; extra == 'numba'
